wis3d/__init__.py
wis3d/server.py
wis3d/utils.py
wis3d/version.py
wis3d/wis3d.py
wis3d/app/out/404.html
wis3d/app/out/favicon.ico
wis3d/app/out/index.html
wis3d/app/out/_next/static/WIYa_t7oYkR4NHTOEx4mr/_buildManifest.js
wis3d/app/out/_next/static/WIYa_t7oYkR4NHTOEx4mr/_ssgManifest.js
wis3d/app/out/_next/static/YjK_7Dy5mNs8f3zznEtm6/_buildManifest.js
wis3d/app/out/_next/static/YjK_7Dy5mNs8f3zznEtm6/_ssgManifest.js
wis3d/app/out/_next/static/chunks/206.a4fdfd7ade11e5172506.js
wis3d/app/out/_next/static/chunks/274.89c388865d8858286c89.js
wis3d/app/out/_next/static/chunks/331-bbcc39df6711dc3bccb5.js
wis3d/app/out/_next/static/chunks/347.23ccbe65680eca15feb1.js
wis3d/app/out/_next/static/chunks/72.c304ee2dea029e0c5511.js
wis3d/app/out/_next/static/chunks/862.3887b0e4da913198cea8.js
wis3d/app/out/_next/static/chunks/9.31b46a033deec674c2b7.js
wis3d/app/out/_next/static/chunks/925.ff87f3099537610191a7.js
wis3d/app/out/_next/static/chunks/978.aaeca35e48d50e8cd5ad.js
wis3d/app/out/_next/static/chunks/commons.0bf1ee3170b7c98e5e7f.js
wis3d/app/out/_next/static/chunks/framework-c93ed74a065331c4bd75.js
wis3d/app/out/_next/static/chunks/main-bc5febc9a145c30e3cff.js
wis3d/app/out/_next/static/chunks/polyfills-a54b4f32bdc1ef890ddd.js
wis3d/app/out/_next/static/chunks/webpack-7ccf594b82a980e22450.js
wis3d/app/out/_next/static/chunks/pages/_app-09b08f0214d5cfc9833c.js
wis3d/app/out/_next/static/chunks/pages/_error-82a806cd39f8ab3dc3ac.js
wis3d/app/out/_next/static/chunks/pages/index-111c2a0d60cac8ab526e.js
wis3d/app/out/images/disc.png
bevis3d-3.0.2.dist-info/METADATA
bevis3d-3.0.2.dist-info/WHEEL
bevis3d-3.0.2.dist-info/entry_points.txt
bevis3d-3.0.2.dist-info/top_level.txt
bevis3d-3.0.2.dist-info/RECORD
