Metadata-Version: 2.1
Name: bevis3d
Version: 3.0.2
Summary: A web-based 3D visualization tool for 3D computer vision.
Author: Linghao Chen, Jingmeng Zhang, Hongcheng Zhao, Zijing Huang, Linghao Chen, Jiaming Sun
License: Apache License 2.0
Project-URL: Homepage, https://wis3d.readthedocs.io/en/latest/
Project-URL: Source Code, https://github.com/zju3dv/wis3d.git
Classifier: Programming Language :: Python :: 3
Classifier: License :: OSI Approved :: MIT License
Classifier: Operating System :: OS Independent
Requires-Python: >=3.6
Requires-Dist: numpy
Requires-Dist: trimesh (>=3.9.0)
Requires-Dist: cherrypy
Requires-Dist: pillow
Requires-Dist: scipy
Requires-Dist: transforms3d
Requires-Dist: torch
Requires-Dist: termcolor
